<?xml version="1.0" encoding="UTF-8"?>
<!DOCTYPE hibernate-mapping PUBLIC "-//Hibernate/Hibernate Mapping DTD 3.0//EN"
                                   "http://www.hibernate.org/dtd/hibernate-mapping-3.0.dtd">
<!-- Generated Dec 8, 2017 3:43:31 AM by Hibernate Tools 5.2.6.Final -->
<hibernate-mapping>
 <class catalog="SHOP" name="com.Entities.Carts" table="Carts">
  <id name="cartId" type="int">
   <column name="Cart_Id"/>
   <generator class="assigned"/>
  </id>
  <many-to-one class="com.Entities.Customers" fetch="select" name="customers">
   <column name="Customer_id"/>
  </many-to-one>
  <many-to-one class="com.Entities.Employees" fetch="select" name="employees">
   <column name="Emp_id"/>
  </many-to-one>
  <many-to-one class="com.Entities.PaymentMethod" fetch="select" name="paymentMethod">
   <column name="Payment_id"/>
  </many-to-one>
  <property generated="never" lazy="false" name="cartDate" type="timestamp">
   <column length="23" name="Cart_date" not-null="true"/>
  </property>
  <property generated="never" lazy="false" name="cartTotal" type="big_decimal">
   <column name="Cart_total" not-null="true" scale="4"/>
  </property>
  <property generated="never" lazy="false" name="shipAddress" type="serializable">
   <column name="Ship_address" not-null="true" sql-type="VARCHAR"/>
  </property>
  <property generated="never" lazy="false" name="shipDate" type="timestamp">
   <column length="23" name="Ship_date" not-null="true"/>
  </property>
  <property generated="never" lazy="false" name="cartStatus" type="int">
   <column name="Cart_status" not-null="true"/>
  </property>
  <property generated="never" lazy="false" name="shipStatus" type="int">
   <column name="Ship_status" not-null="true"/>
  </property>
  <property generated="never" lazy="false" name="payStatus" type="int">
   <column name="Pay_status" not-null="true"/>
  </property>
  <set fetch="select" inverse="true" lazy="true" name="cartDetailses"
   sort="unsorted" table="Cart_Details">
   <key>
    <column name="Cart_id"/>
   </key>
   <one-to-many class="com.Entities.CartDetails"/>
  </set>
 </class>
</hibernate-mapping>
